flocoder/__init__.py
flocoder/codebook_analysis.py
flocoder/codebook_analysis.py.O
flocoder/codecs.py
flocoder/data.py
flocoder/data.py.bak
flocoder/general.py
flocoder/inpainting.py
flocoder/metrics.py
flocoder/ot.py
flocoder/patch_discriminator.py
flocoder/pianoroll.py
flocoder/sampling.py
flocoder/sampling.py.O
flocoder/unet.py
flocoder/viz.py
flocoder/vqgan_plus.py
flocoder/hdit/__init__.py
flocoder/hdit/axial_rope.py
flocoder/hdit/flags.py
flocoder/hdit/flops.py
flocoder/hdit/image_transformer_v2.py
flocoder/hdit/layers.py
flocoder-0.1.1.dist-info/METADATA
flocoder-0.1.1.dist-info/WHEEL
flocoder-0.1.1.dist-info/licenses/LICENSE
flocoder-0.1.1.dist-info/RECORD
