Metadata-Version: 2.4
Name: flocoder
Version: 0.1.1
Summary: A library for teaching and exploring generative latent flow matching
Author-email: "Scott H. Hawley" <scott.hawley@belmont.edu>
License-File: LICENSE
Classifier: License :: OSI Approved :: MIT License
Classifier: Operating System :: OS Independent
Classifier: Programming Language :: Python :: 3
Requires-Python: >=3.9
Requires-Dist: geomloss
Requires-Dist: hydra-core>=1.3.0
Requires-Dist: matplotlib>=3.5.0
Requires-Dist: natten>=0.20.1
Requires-Dist: numpy>=1.20.0
Requires-Dist: pillow>=9.0.0
Requires-Dist: plotly
Requires-Dist: pretty-midi>=0.2.10
Requires-Dist: pyyaml>=6.0
Requires-Dist: scipy>=1.15.3
Requires-Dist: torch>=2.0.0
Requires-Dist: torchmetrics[image]
Requires-Dist: torchvision
Requires-Dist: tqdm>=4.64.0
Requires-Dist: vector-quantize-pytorch>=1.22.4
Requires-Dist: wandb>=0.15.0
Requires-Dist: wheel
Provides-Extra: dev
Requires-Dist: gradio>=4.0.0; extra == 'dev'
Requires-Dist: hydra-colorlog>=1.2.0; extra == 'dev'
Requires-Dist: jupyter>=1.0.0; extra == 'dev'
Requires-Dist: midi-player; extra == 'dev'
Requires-Dist: pytest>=7.0.0; extra == 'dev'
